pyroll/ring_model_thermal/__init__.py
pyroll/ring_model_thermal/config.py
pyroll/ring_model_thermal/cooling_pipe.py
pyroll/ring_model_thermal/profile.py
pyroll/ring_model_thermal/report.py
pyroll/ring_model_thermal/roll_pass.py
pyroll/ring_model_thermal/transport.py
pyroll_ring_model_thermal-3.0.2.dist-info/METADATA
pyroll_ring_model_thermal-3.0.2.dist-info/WHEEL
pyroll_ring_model_thermal-3.0.2.dist-info/licenses/LICENSE
pyroll_ring_model_thermal-3.0.2.dist-info/RECORD
