Metadata-Version: 2.4
Name: pyroll-ring-model-thermal
Version: 3.0.2
Summary: Plugin for PyRolL providing a radial thermal approach based on the ring model.
Author-email: Max Weiner <max.weiner@imf.tu-freiberg.de>, Christoph Renzing <christoph.renzing@imf.tu-freiberg.de>
License-Expression: BSD-3-Clause
License-File: LICENSE
Requires-Python: <4.0,>=3.9
Requires-Dist: pyroll-core~=3.0
Requires-Dist: pyroll-ring-model~=3.0
